willspeak/__init__.py
willspeak/__main__.py
willspeak/audio.py
willspeak/client.py
willspeak/conf.py
willspeak/dataobjects.py
willspeak/filters.py
willspeak/monitors.py
willspeak/scripts.py
willspeak/server.py
willspeak/tts/__init__.py
willspeak/tts/sapi5.py
willspeak/utils.py
willspeak-0.4.0.dist-info/LICENSE
willspeak-0.4.0.dist-info/METADATA
willspeak-0.4.0.dist-info/WHEEL
willspeak-0.4.0.dist-info/entry_points.txt
willspeak-0.4.0.dist-info/RECORD
