Metadata-Version: 2.1
Name: willspeak
Version: 0.4.0
Summary: Python Text to Speach using Microsoft Sapi5 with a server/client model
Home-page: https://github.com/willforde/willspeek.git
License: GPL-2.0-only
Keywords: tts,sapi5,speech,voice
Author: willforde
Author-email: willforde@gmail.com
Requires-Python: >=3.10,<4.0
Classifier: Development Status :: 3 - Alpha
Classifier: Environment :: No Input/Output (Daemon)
Classifier: License :: OSI Approved :: GNU General Public License v2 (GPLv2)
Classifier: Natural Language :: English
Classifier: Operating System :: Microsoft :: Windows
Classifier: Operating System :: POSIX :: Linux
Classifier: Programming Language :: Python :: 3
Classifier: Programming Language :: Python :: 3.10
Classifier: Programming Language :: Python :: 3.11
Classifier: Programming Language :: Python :: 3 :: Only
Classifier: Programming Language :: Python :: 3.10
Classifier: Programming Language :: Python :: 3.11
Classifier: Programming Language :: Python :: 3.12
Classifier: Topic :: Multimedia :: Sound/Audio :: Sound Synthesis
Requires-Dist: appdirs (>=1.4.4,<2.0.0)
Requires-Dist: colorama (>=0.4.6,<0.5.0)
Requires-Dist: comtypes (>=1.1.14,<2.0.0) ; sys_platform == "win32"
Requires-Dist: nltk (>=3.7,<4.0)
Requires-Dist: pyaudio (>=0.2.12,<0.3.0)
Requires-Dist: pyclip (>=0.7.0,<0.8.0)
Requires-Dist: pydantic (>=1.10.2,<2.0.0)
Requires-Dist: pywin32 (>=305,<306) ; sys_platform == "win32"
Requires-Dist: requests (>=2.28.1,<3.0.0)
Requires-Dist: starlette (>=0.22.0,<0.23.0)
Requires-Dist: uvicorn (>=0.20.0,<0.21.0)
Project-URL: Bug Tracker, https://github.com/willforde/willspeek/issues
Project-URL: Repository, https://github.com/willforde/willspeek.git
